{"events":[{"name":"Layout","ts":103861569261,"dirtyObjects":1,"dur":200,"hasStackTrace":false,"stackTrace":[]},{"name":"ScheduleStyleRecalculation","ts":103861717628},{"name":"InvalidateLayout","ts":103861722533},{"name":"InvalidateLayout","ts":103861722844},{"name":"Layout","ts":103861722881,"dirtyObjects":7,"dur":214252,"hasStackTrace":true,"stackTrace":[{"functionName":"","scriptId":"7","url":"https://duckduckgo.com/lib/l113.js","lineNumber":1,"columnNumber":2759}]},{"name":"ScheduleStyleRecalculation","ts":103861937205},{"name":"InvalidateLayout","ts":103861937222},{"name":"InvalidateLayout","ts":103861938283},{"name":"Layout","ts":103861938322,"dirtyObjects":5,"dur":100,"hasStackTrace":true,"stackTrace":[{"functionName":"","scriptId":"7","url":"https://duckduckgo.com/lib/l113.js","lineNumber":1,"columnNumber":3066}]},{"name":"InvalidateLayout","ts":103861938451},{"name":"InvalidateLayout","ts":103861938476},{"name":"ScheduleStyleRecalculation","ts":103861938497},{"name":"Layout","ts":103861968682,"dirtyObjects":3,"dur":150,"hasStackTrace":true,"stackTrace":[{"functionName":"_updateScreenSize","scriptId":"5","url":"https://duckduckgo.com/d2742.js","lineNumber":1,"columnNumber":27497}]},{"name":"ScheduleStyleRecalculation","ts":103861977634},{"name":"InvalidateLayout","ts":103862186575},{"name":"InvalidateLayout","ts":103862186604},{"name":"Layout","ts":103862187053,"dirtyObjects":61,"dur":353187,"hasStackTrace":false,"stackTrace":[]},{"name":"UpdateLayerTree","dur":330,"ts":103862540262},{"name":"HitTest","ts":103862540600,"dur":37,"x":1638,"y":798,"nodeName":"BODY class='body--serp'","move":true},{"name":"UpdateLayerTree","dur":70,"ts":103862540820},{"name":"HitTest","ts":103862540895,"dur":7,"x":1638,"y":798,"nodeName":"BODY class='body--serp'","move":true},{"name":"UpdateLayerTree","dur":4,"ts":103862540970},{"name":"ScheduleStyleRecalculation","ts":103862542929},{"name":"InvalidateLayout","ts":103862546903},{"name":"Layout","ts":103862549060,"dirtyObjects":63,"dur":951,"hasStackTrace":false,"stackTrace":[]},{"name":"UpdateLayerTree","dur":310,"ts":103862550037},{"name":"ScheduleStyleRecalculation","ts":103862554360},{"name":"InvalidateLayout","ts":103862555123},{"name":"Layout","ts":103862555263,"dirtyObjects":24,"dur":84,"hasStackTrace":false,"stackTrace":[]},{"name":"UpdateLayerTree","dur":37,"ts":103862555553},{"name":"HitTest","ts":103862555592,"dur":32,"x":1638,"y":798,"nodeName":"BODY class='body--serp'","move":true},{"name":"UpdateLayerTree","dur":4,"ts":103862555650},{"name":"InvalidateLayout","ts":103862555731},{"name":"InvalidateLayout","ts":103862555741},{"name":"Layout","ts":103862555925,"dirtyObjects":2,"dur":33,"hasStackTrace":false,"stackTrace":[]},{"name":"UpdateLayerTree","dur":65,"ts":103862555966},{"name":"UpdateLayerTree","dur":28,"ts":103862573634},{"name":"ScheduleStyleRecalculation","ts":103862598304},{"name":"InvalidateLayout","ts":103862608280},{"name":"Layout","ts":103862608391,"dirtyObjects":6,"dur":134,"hasStackTrace":true,"stackTrace":[{"functionName":"bJ.expr.filters.hidden","scriptId":"7","url":"https://duckduckgo.com/lib/l113.js","lineNumber":26,"columnNumber":69719}]},{"name":"ScheduleStyleRecalculation","ts":103862609689},{"name":"InvalidateLayout","ts":103862609756},{"name":"InvalidateLayout","ts":103862634870},{"name":"InvalidateLayout","ts":103862635087},{"name":"Layout","ts":103862635140,"dirtyObjects":83,"dur":885,"hasStackTrace":true,"stackTrace":[{"functionName":"get","scriptId":"7","url":"https://duckduckgo.com/lib/l113.js","lineNumber":26,"columnNumber":68505}]},{"name":"ScheduleStyleRecalculation","ts":103862638607},{"name":"InvalidateLayout","ts":103862655584},{"name":"ScheduleStyleRecalculation","ts":103862657947},{"name":"ScheduleStyleRecalculation","ts":103862658262},{"name":"Layout","ts":103862674813,"dirtyObjects":161,"dur":1276465,"hasStackTrace":true,"stackTrace":[{"functionName":"c.Views.Modules.About","scriptId":"12","url":"https://duckduckgo.com/g2262.js","lineNumber":1,"columnNumber":300650}]},{"name":"ScheduleStyleRecalculation","ts":103863951443},{"name":"InvalidateLayout","ts":103863951846},{"name":"ScheduleStyleRecalculation","ts":103863952042},{"name":"Layout","ts":103863962989,"dirtyObjects":11,"dur":396,"hasStackTrace":false,"stackTrace":[]},{"name":"UpdateLayerTree","dur":1343,"ts":103863963606},{"name":"HitTest","ts":103863964979,"dur":223,"x":1638,"y":798,"nodeName":"DIV class='site-wrapper js-site-wrapper'","move":true},{"name":"UpdateLayerTree","dur":13,"ts":103863965374},{"name":"UpdateLayerTree","dur":61,"ts":103863979240},{"name":"HitTest","ts":103863979305,"dur":9,"x":1638,"y":798,"nodeName":"DIV class='site-wrapper js-site-wrapper'","move":true},{"name":"UpdateLayerTree","dur":5,"ts":103863979349},{"name":"ScheduleStyleRecalculation","ts":103863996702},{"name":"InvalidateLayout","ts":103863996758},{"name":"InvalidateLayout","ts":103863996855},{"name":"InvalidateLayout","ts":103864002909},{"name":"Layout","ts":103864003038,"dirtyObjects":10,"dur":142,"hasStackTrace":false,"stackTrace":[]},{"name":"ScheduleStyleRecalculation","ts":103864005109},{"name":"InvalidateLayout","ts":103864005610},{"name":"Layout","ts":103864005709,"dirtyObjects":6,"dur":298,"hasStackTrace":false,"stackTrace":[]},{"name":"InvalidateLayout","ts":103864008098},{"name":"Layout","ts":103864008192,"dirtyObjects":3,"dur":83,"hasStackTrace":false,"stackTrace":[]},{"name":"ScheduleStyleRecalculation","ts":103864009934},{"name":"InvalidateLayout","ts":103864010129},{"name":"Layout","ts":103864010200,"dirtyObjects":6,"dur":76,"hasStackTrace":false,"stackTrace":[]},{"name":"ScheduleStyleRecalculation","ts":103864011500},{"name":"InvalidateLayout","ts":103864011677},{"name":"Layout","ts":103864011754,"dirtyObjects":6,"dur":144,"hasStackTrace":false,"stackTrace":[]},{"name":"InvalidateLayout","ts":103864012895},{"name":"Layout","ts":103864017010,"dirtyObjects":282,"dur":3080,"hasStackTrace":false,"stackTrace":[]},{"name":"UpdateLayerTree","dur":979,"ts":103864020129},{"name":"InvalidateLayout","ts":103864021346},{"name":"InvalidateLayout","ts":103864021357},{"name":"Layout","ts":103864021566,"dirtyObjects":2,"dur":110,"hasStackTrace":false,"stackTrace":[]},{"name":"UpdateLayerTree","dur":79,"ts":103864021690},{"name":"InvalidateLayout","ts":103864022240},{"name":"InvalidateLayout","ts":103864022250},{"name":"Layout","ts":103864022420,"dirtyObjects":2,"dur":110,"hasStackTrace":false,"stackTrace":[]},{"name":"UpdateLayerTree","dur":93,"ts":103864022543},{"name":"InvalidateLayout","ts":103864022758},{"name":"InvalidateLayout","ts":103864022765},{"name":"Layout","ts":103864022991,"dirtyObjects":2,"dur":89,"hasStackTrace":false,"stackTrace":[]},{"name":"UpdateLayerTree","dur":94,"ts":103864023092},{"name":"InvalidateLayout","ts":103864023304},{"name":"InvalidateLayout","ts":103864023312},{"name":"Layout","ts":103864023464,"dirtyObjects":2,"dur":82,"hasStackTrace":false,"stackTrace":[]},{"name":"UpdateLayerTree","dur":75,"ts":103864023574},{"name":"InvalidateLayout","ts":103864023739},{"name":"InvalidateLayout","ts":103864023747},{"name":"Layout","ts":103864023933,"dirtyObjects":2,"dur":76,"hasStackTrace":false,"stackTrace":[]},{"name":"UpdateLayerTree","dur":73,"ts":103864024022},{"name":"UpdateLayerTree","dur":8,"ts":103864024614},{"name":"UpdateLayerTree","dur":21,"ts":103864027511},{"name":"InvalidateLayout","ts":103864030938},{"name":"Layout","ts":103864031079,"dirtyObjects":17,"dur":191,"hasStackTrace":false,"stackTrace":[]},{"name":"InvalidateLayout","ts":103864031511},{"name":"UpdateLayerTree","dur":37,"ts":103864032412},{"name":"ScheduleStyleRecalculation","ts":103864036494},{"name":"InvalidateLayout","ts":103864037296},{"name":"Layout","ts":103864037550,"dirtyObjects":23,"dur":294,"hasStackTrace":false,"stackTrace":[]},{"name":"UpdateLayerTree","dur":20,"ts":103864038409},{"name":"UpdateLayerTree","dur":27,"ts":103864039948},{"name":"UpdateLayerTree","dur":17,"ts":103864041449},{"name":"Layout","ts":103864041869,"dirtyObjects":10,"dur":496,"hasStackTrace":false,"stackTrace":[]},{"name":"UpdateLayerTree","dur":190,"ts":103864042457},{"name":"HitTest","ts":103864042654,"dur":206,"x":1638,"y":798,"nodeName":"DIV class='site-wrapper js-site-wrapper'","move":true},{"name":"UpdateLayerTree","dur":10,"ts":103864042936},{"name":"InvalidateLayout","ts":103864043100},{"name":"InvalidateLayout","ts":103864043122},{"name":"Layout","ts":103864043397,"dirtyObjects":2,"dur":102,"hasStackTrace":false,"stackTrace":[]},{"name":"UpdateLayerTree","dur":93,"ts":103864043519},{"name":"InvalidateLayout","ts":103864043854},{"name":"InvalidateLayout","ts":103864043865},{"name":"Layout","ts":103864044032,"dirtyObjects":2,"dur":131,"hasStackTrace":false,"stackTrace":[]},{"name":"UpdateLayerTree","dur":87,"ts":103864044175},{"name":"ScheduleStyleRecalculation","ts":103864050907},{"name":"ScheduleStyleRecalculation","ts":103864058820},{"name":"InvalidateLayout","ts":103864066061},{"name":"InvalidateLayout","ts":103864066088},{"name":"Layout","ts":103864066160,"dirtyObjects":11,"dur":328,"hasStackTrace":true,"stackTrace":[{"functionName":"nrb","scriptId":"5","url":"https://duckduckgo.com/d2742.js","lineNumber":1,"columnNumber":114927}]},{"name":"ScheduleStyleRecalculation","ts":103864090338},{"name":"InvalidateLayout","ts":103864099822},{"name":"Layout","ts":103864100621,"dirtyObjects":401,"dur":2893,"hasStackTrace":true,"stackTrace":[{"functionName":"bJ.fn.offset","scriptId":"7","url":"https://duckduckgo.com/lib/l113.js","lineNumber":26,"columnNumber":91846}]},{"name":"ScheduleStyleRecalculation","ts":103864105599},{"name":"UpdateLayerTree","dur":11,"ts":103864118073},{"name":"UpdateLayerTree","dur":5,"ts":103864118165},{"name":"InvalidateLayout","ts":103864118882},{"name":"InvalidateLayout","ts":103864119066},{"name":"Layout","ts":103864119138,"dirtyObjects":58,"dur":929,"hasStackTrace":false,"stackTrace":[]},{"name":"Layout","ts":103864120089,"dirtyObjects":1,"dur":41,"hasStackTrace":false,"stackTrace":[]},{"name":"UpdateLayerTree","dur":1252,"ts":103864120170},{"name":"HitTest","ts":103864121432,"dur":76,"x":1638,"y":798,"nodeName":"DIV class='result__body links_main links_deep'","move":true},{"name":"UpdateLayerTree","dur":9,"ts":103864122466},{"name":"UpdateLayerTree","dur":6,"ts":103864122603},{"name":"UpdateLayerTree","dur":4,"ts":103864122734},{"name":"UpdateLayerTree","dur":5,"ts":103864122851},{"name":"UpdateLayerTree","dur":5,"ts":103864122995},{"name":"UpdateLayerTree","dur":5,"ts":103864123062},{"name":"UpdateLayerTree","dur":4,"ts":103864123131},{"name":"UpdateLayerTree","dur":11,"ts":103864123195},{"name":"UpdateLayerTree","dur":20,"ts":103864128396},{"name":"HitTest","ts":103864128419,"dur":10,"x":1638,"y":798,"nodeName":"DIV class='result__body links_main links_deep'","move":true},{"name":"UpdateLayerTree","dur":16,"ts":103864128471},{"name":"ScheduleStyleRecalculation","ts":103864134042},{"name":"InvalidateLayout","ts":103864135275},{"name":"Layout","ts":103864135426,"dirtyObjects":50,"dur":780,"hasStackTrace":true,"stackTrace":[{"functionName":"c.Views.Modules.About","scriptId":"12","url":"https://duckduckgo.com/g2262.js","lineNumber":1,"columnNumber":300650}]},{"name":"ScheduleStyleRecalculation","ts":103864136405},{"name":"InvalidateLayout","ts":103864136936},{"name":"ScheduleStyleRecalculation","ts":103864137161},{"name":"Layout","ts":103864139120,"dirtyObjects":11,"dur":376,"hasStackTrace":false,"stackTrace":[]},{"name":"UpdateLayerTree","dur":660,"ts":103864139524},{"name":"HitTest","ts":103864140191,"dur":125,"x":1638,"y":798,"nodeName":"DIV class='module__content js-about-module-content'","move":true},{"name":"UpdateLayerTree","dur":9,"ts":103864140848},{"name":"ScheduleStyleRecalculation","ts":103864168641},{"name":"InvalidateLayout","ts":103864175668},{"name":"Layout","ts":103864179839,"dirtyObjects":43,"dur":3495,"hasStackTrace":true,"stackTrace":[{"functionName":"prop","scriptId":"7","url":"https://duckduckgo.com/lib/l113.js","lineNumber":26,"columnNumber":35368}]},{"name":"ScheduleStyleRecalculation","ts":103864187035},{"name":"UpdateLayerTree","dur":3243,"ts":103864196052},{"name":"HitTest","ts":103864199362,"dur":266,"x":1638,"y":798,"nodeName":"DIV class='module__content js-about-module-content'","move":true},{"name":"UpdateLayerTree","dur":55,"ts":103864199832},{"name":"UpdateLayerTree","dur":15,"ts":103864200308},{"name":"UpdateLayerTree","dur":24,"ts":103864200848},{"name":"UpdateLayerTree","dur":23,"ts":103864201318},{"name":"UpdateLayerTree","dur":16,"ts":103864201638},{"name":"UpdateLayerTree","dur":8,"ts":103864201741},{"name":"UpdateLayerTree","dur":5,"ts":103864201945},{"name":"UpdateLayerTree","dur":27,"ts":103864202042},{"name":"ScheduleStyleRecalculation","ts":103864210978},{"name":"InvalidateLayout","ts":103864214222},{"name":"Layout","ts":103864214681,"dirtyObjects":16,"dur":2743,"hasStackTrace":false,"stackTrace":[]},{"name":"UpdateLayerTree","dur":1128,"ts":103864217575},{"name":"UpdateLayerTree","dur":115,"ts":103864324702},{"name":"HitTest","ts":103864324839,"dur":139,"x":1638,"y":798,"nodeName":"DIV class='module__content js-about-module-content'","move":true},{"name":"UpdateLayerTree","dur":5,"ts":103864325014},{"name":"UpdateLayerTree","dur":212,"ts":103864329420},{"name":"UpdateLayerTree","dur":67,"ts":103864342343},{"name":"UpdateLayerTree","dur":75,"ts":103864366797},{"name":"UpdateLayerTree","dur":12,"ts":103864717719},{"name":"HitTest","ts":103864717734,"dur":154,"x":1639,"y":797,"nodeName":"DIV class='module__content js-about-module-content'","move":true},{"name":"UpdateLayerTree","dur":7,"ts":103864718224},{"name":"UpdateLayerTree","dur":69,"ts":103864725756},{"name":"HitTest","ts":103864725830,"dur":196,"x":1639,"y":796,"nodeName":"DIV class='module__content js-about-module-content'","move":true},{"name":"UpdateLayerTree","dur":16,"ts":103864726588},{"name":"UpdateLayerTree","dur":16,"ts":103864742364},{"name":"HitTest","ts":103864742383,"dur":122,"x":1639,"y":794,"nodeName":"DIV class='module__content js-about-module-content'","move":true},{"name":"UpdateLayerTree","dur":7,"ts":103864742821},{"name":"UpdateLayerTree","dur":22,"ts":103864759055},{"name":"HitTest","ts":103864759080,"dur":135,"x":1632,"y":791,"nodeName":"DIV class='module__content js-about-module-content'","move":true},{"name":"UpdateLayerTree","dur":17,"ts":103864759545},{"name":"UpdateLayerTree","dur":52,"ts":103864775860},{"name":"HitTest","ts":103864775916,"dur":168,"x":1623,"y":786,"nodeName":"DIV class='module__content js-about-module-content'","move":true},{"name":"UpdateLayerTree","dur":13,"ts":103864776660},{"name":"UpdateLayerTree","dur":31,"ts":103864792310},{"name":"HitTest","ts":103864792345,"dur":146,"x":1608,"y":780,"nodeName":"DIV class='module__content js-about-module-content'","move":true},{"name":"UpdateLayerTree","dur":13,"ts":103864792770},{"name":"UpdateLayerTree","dur":17,"ts":103864808914},{"name":"HitTest","ts":103864808934,"dur":123,"x":1598,"y":776,"nodeName":"DIV class='module__content js-about-module-content'","move":true},{"name":"UpdateLayerTree","dur":17,"ts":103864809290},{"name":"UpdateLayerTree","dur":34,"ts":103864825685},{"name":"HitTest","ts":103864825722,"dur":222,"x":1587,"y":772,"nodeName":"DIV id='links_wrapper' class='serp__results js-serp-results'","move":true},{"name":"UpdateLayerTree","dur":34,"ts":103864826418},{"name":"UpdateLayerTree","dur":12,"ts":103864842256},{"name":"HitTest","ts":103864842270,"dur":130,"x":1572,"y":769,"nodeName":"DIV id='links_wrapper' class='serp__results js-serp-results'","move":true},{"name":"UpdateLayerTree","dur":10,"ts":103864842647},{"name":"UpdateLayerTree","dur":17,"ts":103864859163},{"name":"HitTest","ts":103864859183,"dur":157,"x":1562,"y":765,"nodeName":"DIV id='links_wrapper' class='serp__results js-serp-results'","move":true},{"name":"UpdateLayerTree","dur":29,"ts":103864859785},{"name":"UpdateLayerTree","dur":78,"ts":103864875760},{"name":"HitTest","ts":103864875841,"dur":183,"x":1552,"y":760,"nodeName":"DIV id='links_wrapper' class='serp__results js-serp-results'","move":true},{"name":"UpdateLayerTree","dur":16,"ts":103864876419},{"name":"UpdateLayerTree","dur":13,"ts":103864892366},{"name":"HitTest","ts":103864892381,"dur":157,"x":1539,"y":755,"nodeName":"DIV id='links_wrapper' class='serp__results js-serp-results'","move":true},{"name":"UpdateLayerTree","dur":8,"ts":103864892806},{"name":"UpdateLayerTree","dur":7,"ts":103864909053},{"name":"HitTest","ts":103864909062,"dur":112,"x":1520,"y":745,"nodeName":"DIV id='links_wrapper' class='serp__results js-serp-results'","move":true},{"name":"UpdateLayerTree","dur":27,"ts":103864909374},{"name":"UpdateLayerTree","dur":7,"ts":103864925640},{"name":"HitTest","ts":103864925649,"dur":107,"x":1507,"y":738,"nodeName":"DIV id='links_wrapper' class='serp__results js-serp-results'","move":true},{"name":"UpdateLayerTree","dur":5,"ts":103864925985},{"name":"UpdateLayerTree","dur":7,"ts":103864942384},{"name":"HitTest","ts":103864942394,"dur":179,"x":1497,"y":732,"nodeName":"DIV id='links_wrapper' class='serp__results js-serp-results'","move":true},{"name":"UpdateLayerTree","dur":5,"ts":103864942845},{"name":"UpdateLayerTree","dur":6,"ts":103864958911},{"name":"HitTest","ts":103864958919,"dur":87,"x":1487,"y":725,"nodeName":"DIV class='module--carousel__image is-center-image'","move":true},{"name":"ScheduleStyleRecalculation","ts":103864959846},{"name":"UpdateLayerTree","dur":161,"ts":103864960289},{"name":"UpdateLayerTree","dur":13,"ts":103864975635},{"name":"HitTest","ts":103864975651,"dur":136,"x":1482,"y":720,"nodeName":"DIV class='module--carousel__image is-center-image'","move":true},{"name":"UpdateLayerTree","dur":7,"ts":103864976098},{"name":"UpdateLayerTree","dur":11,"ts":103864992491},{"name":"HitTest","ts":103864992504,"dur":120,"x":1477,"y":712,"nodeName":"DIV class='module--carousel__image is-center-image'","move":true},{"name":"UpdateLayerTree","dur":30,"ts":103864992922},{"name":"UpdateLayerTree","dur":8,"ts":103865009195},{"name":"HitTest","ts":103865009206,"dur":113,"x":1470,"y":702,"nodeName":"DIV class='module--carousel__image is-center-image'","move":true},{"name":"UpdateLayerTree","dur":8,"ts":103865009609},{"name":"UpdateLayerTree","dur":7,"ts":103865025695},{"name":"HitTest","ts":103865025704,"dur":127,"x":1463,"y":680,"nodeName":"DIV class='module--carousel__image is-center-image'","move":true},{"name":"UpdateLayerTree","dur":5,"ts":103865026064},{"name":"UpdateLayerTree","dur":11,"ts":103865042292},{"name":"HitTest","ts":103865042305,"dur":113,"x":1460,"y":666,"nodeName":"DIV class='module--carousel__image is-center-image'","move":true},{"name":"UpdateLayerTree","dur":5,"ts":103865042668},{"name":"UpdateLayerTree","dur":8,"ts":103865058972},{"name":"HitTest","ts":103865058982,"dur":117,"x":1460,"y":650,"nodeName":"DIV class='module--carousel__image is-center-image'","move":true},{"name":"UpdateLayerTree","dur":41,"ts":103865059392},{"name":"UpdateLayerTree","dur":12,"ts":103865075570},{"name":"HitTest","ts":103865075584,"dur":93,"x":1460,"y":619,"nodeName":"DIV class='module--carousel__image is-center-image'","move":true},{"name":"UpdateLayerTree","dur":14,"ts":103865075916},{"name":"UpdateLayerTree","dur":11,"ts":103865092266},{"name":"HitTest","ts":103865092279,"dur":91,"x":1460,"y":600,"nodeName":"DIV class='module--carousel__image is-center-image'","move":true},{"name":"UpdateLayerTree","dur":11,"ts":103865092557},{"name":"UpdateLayerTree","dur":8,"ts":103865108988},{"name":"HitTest","ts":103865108998,"dur":99,"x":1462,"y":579,"nodeName":"DIV class='module--carousel__image is-center-image'","move":true},{"name":"UpdateLayerTree","dur":5,"ts":103865109297},{"name":"UpdateLayerTree","dur":12,"ts":103865125652},{"name":"HitTest","ts":103865125666,"dur":91,"x":1481,"y":553,"nodeName":"DIV class='module--carousel__image is-center-image'","move":true},{"name":"UpdateLayerTree","dur":6,"ts":103865126025},{"name":"UpdateLayerTree","dur":8,"ts":103865142250},{"name":"HitTest","ts":103865142261,"dur":108,"x":1525,"y":512,"nodeName":"DIV id='links_wrapper' class='serp__results js-serp-results'","move":true},{"name":"ScheduleStyleRecalculation","ts":103865142845},{"name":"UpdateLayerTree","dur":124,"ts":103865143440},{"name":"UpdateLayerTree","dur":14,"ts":103865159062},{"name":"HitTest","ts":103865159078,"dur":151,"x":1560,"y":484,"nodeName":"DIV id='links_wrapper' class='serp__results js-serp-results'","move":true},{"name":"UpdateLayerTree","dur":15,"ts":103865159576},{"name":"UpdateLayerTree","dur":29,"ts":103865175817},{"name":"HitTest","ts":103865175849,"dur":123,"x":1598,"y":457,"nodeName":"DIV class='module__content js-about-module-content'","move":true},{"name":"UpdateLayerTree","dur":5,"ts":103865176313},{"name":"UpdateLayerTree","dur":9,"ts":103865192375},{"name":"HitTest","ts":103865192386,"dur":108,"x":1633,"y":431,"nodeName":"DIV class='module__content js-about-module-content'","move":true},{"name":"UpdateLayerTree","dur":5,"ts":103865192705},{"name":"UpdateLayerTree","dur":9,"ts":103865208958},{"name":"HitTest","ts":103865208969,"dur":106,"x":1693,"y":404,"nodeName":"DIV class='module__text'","move":true},{"name":"UpdateLayerTree","dur":6,"ts":103865209382},{"name":"UpdateLayerTree","dur":20,"ts":103865225897},{"name":"HitTest","ts":103865225920,"dur":118,"x":1734,"y":392,"nodeName":"#text","move":true},{"name":"ScheduleStyleRecalculation","ts":103865226055},{"name":"UpdateLayerTree","dur":16,"ts":103865226864},{"name":"UpdateLayerTree","dur":18,"ts":103865242330},{"name":"HitTest","ts":103865242351,"dur":117,"x":1776,"y":382,"nodeName":"#text","move":true},{"name":"UpdateLayerTree","dur":16,"ts":103865242684},{"name":"UpdateLayerTree","dur":19,"ts":103865258992},{"name":"HitTest","ts":103865259014,"dur":92,"x":1850,"y":375,"nodeName":"#text","move":true},{"name":"UpdateLayerTree","dur":13,"ts":103865259335},{"name":"UpdateLayerTree","dur":14,"ts":103865275673},{"name":"HitTest","ts":103865275689,"dur":124,"x":1902,"y":367,"nodeName":"DIV class='module__title js-about-item-title'","move":true},{"name":"ScheduleStyleRecalculation","ts":103865275824},{"name":"UpdateLayerTree","dur":33,"ts":103865276187},{"name":"UpdateLayerTree","dur":8,"ts":103865292293},{"name":"HitTest","ts":103865292303,"dur":86,"x":1965,"y":362,"nodeName":"DIV class='module__title js-about-item-title'","move":true},{"name":"UpdateLayerTree","dur":5,"ts":103865292589},{"name":"UpdateLayerTree","dur":7,"ts":103865308958},{"name":"HitTest","ts":103865308967,"dur":81,"x":2036,"y":359,"nodeName":"DIV class='module__title js-about-item-title'","move":true},{"name":"UpdateLayerTree","dur":6,"ts":103865309355},{"name":"UpdateLayerTree","dur":10,"ts":103865325571},{"name":"HitTest","ts":103865325583,"dur":81,"x":2158,"y":359,"nodeName":"DIV class='module__title js-about-item-title'","move":true},{"name":"UpdateLayerTree","dur":5,"ts":103865325922},{"name":"UpdateLayerTree","dur":6,"ts":103865342326},{"name":"HitTest","ts":103865342334,"dur":78,"x":2252,"y":359,"nodeName":"DIV class='module__title js-about-item-title'","move":true},{"name":"UpdateLayerTree","dur":5,"ts":103865342590},{"name":"UpdateLayerTree","dur":8,"ts":103865358939},{"name":"HitTest","ts":103865358949,"dur":87,"x":2359,"y":359,"nodeName":"DIV class='module__title js-about-item-title'","move":true},{"name":"UpdateLayerTree","dur":8,"ts":103865359215},{"name":"UpdateLayerTree","dur":7,"ts":103865375574},{"name":"HitTest","ts":103865375583,"dur":102,"x":2542,"y":363,"nodeName":"DIV id='links_wrapper' class='serp__results js-serp-results'","move":true},{"name":"UpdateLayerTree","dur":7,"ts":103865375928},{"name":"UpdateLayerTree","dur":6,"ts":103865392220},{"name":"HitTest","ts":103865392234,"dur":137,"x":2674,"y":391,"nodeName":"DIV id='web_content_wrapper' class='content-wrap'","move":true},{"name":"UpdateLayerTree","dur":27,"ts":103865392563},{"name":"UpdateLayerTree","dur":6,"ts":103865408944},{"name":"HitTest","ts":103865408952,"dur":91,"x":2798,"y":416,"nodeName":"DIV id='web_content_wrapper' class='content-wrap'","move":true},{"name":"UpdateLayerTree","dur":28,"ts":103865409211},{"name":"UpdateLayerTree","dur":6,"ts":103865425570},{"name":"HitTest","ts":103865425578,"dur":88,"x":2917,"y":437,"nodeName":"DIV id='web_content_wrapper' class='content-wrap'","move":true},{"name":"UpdateLayerTree","dur":7,"ts":103865425836},{"name":"UpdateLayerTree","dur":8,"ts":103865442207},{"name":"HitTest","ts":103865442217,"dur":106,"x":3072,"y":462,"nodeName":"DIV id='web_content_wrapper' class='content-wrap'","move":true},{"name":"UpdateLayerTree","dur":8,"ts":103865442512},{"name":"UpdateLayerTree","dur":7,"ts":103865458935},{"name":"HitTest","ts":103865458944,"dur":109,"x":3158,"y":475,"nodeName":"DIV id='web_content_wrapper' class='content-wrap'","move":true},{"name":"UpdateLayerTree","dur":26,"ts":103865459220},{"name":"UpdateLayerTree","dur":7,"ts":103865475711},{"name":"HitTest","ts":103865475721,"dur":186,"x":3227,"y":486,"nodeName":"DIV id='web_content_wrapper' class='content-wrap'","move":true},{"name":"UpdateLayerTree","dur":7,"ts":103865476211},{"name":"UpdateLayerTree","dur":14,"ts":103865492278},{"name":"HitTest","ts":103865492295,"dur":103,"x":3263,"y":492,"nodeName":"DIV id='web_content_wrapper' class='content-wrap'","move":true},{"name":"UpdateLayerTree","dur":7,"ts":103865492579},{"name":"UpdateLayerTree","dur":11,"ts":103865821696},{"name":"HitTest","ts":103865821709,"dur":198,"x":3263,"y":490,"nodeName":"DIV id='web_content_wrapper' class='content-wrap'","move":true},{"name":"UpdateLayerTree","dur":27,"ts":103865822116},{"name":"UpdateLayerTree","dur":7,"ts":103865828509},{"name":"HitTest","ts":103865828518,"dur":96,"x":3263,"y":485,"nodeName":"DIV id='web_content_wrapper' class='content-wrap'","move":true},{"name":"UpdateLayerTree","dur":6,"ts":103865828757},{"name":"UpdateLayerTree","dur":6,"ts":103865842335},{"name":"HitTest","ts":103865842343,"dur":103,"x":3268,"y":477,"nodeName":"DIV id='web_content_wrapper' class='content-wrap'","move":true},{"name":"UpdateLayerTree","dur":29,"ts":103865842584},{"name":"UpdateLayerTree","dur":10,"ts":103865859012},{"name":"HitTest","ts":103865859042,"dur":194,"x":3297,"y":443,"nodeName":"DIV id='web_content_wrapper' class='content-wrap'","move":true},{"name":"UpdateLayerTree","dur":7,"ts":103865859424},{"name":"UpdateLayerTree","dur":7,"ts":103865875655},{"name":"HitTest","ts":103865875664,"dur":98,"x":3319,"y":419,"nodeName":"DIV id='web_content_wrapper' class='content-wrap'","move":true},{"name":"UpdateLayerTree","dur":27,"ts":103865875970},{"name":"UpdateLayerTree","dur":10,"ts":103865892343},{"name":"HitTest","ts":103865892355,"dur":103,"x":3338,"y":399,"nodeName":"HTML class='has-zcm js no-touch opacity csstransforms3d csstransitions svg cssfilters is-not-mobile-device full-urls has-footer has-right-rail-module has-right-rail-ads'","move":true},{"name":"UpdateLayerTree","dur":42,"ts":103865892545},{"name":"UpdateLayerTree","dur":15,"ts":103865909216},{"name":"HitTest","ts":103865909234,"dur":192,"x":3352,"y":381,"nodeName":"HTML class='has-zcm js no-touch opacity csstransforms3d csstransitions svg cssfilters is-not-mobile-device full-urls has-footer has-right-rail-module has-right-rail-ads'","move":true},{"name":"UpdateLayerTree","dur":42,"ts":103865909625},{"name":"UpdateLayerTree","dur":13,"ts":103866670254},{"name":"UpdateLayerTree","dur":8,"ts":103858803299},{"name":"HitTest","ts":103858803310,"dur":29,"x":3351,"y":75,"nodeName":"BODY id='pg-chrome_newtab' class='page-chrome_newtab body--home'","move":true},{"name":"UpdateLayerTree","dur":5,"ts":103858803464},{"name":"UpdateLayerTree","dur":11,"ts":103858820245},{"name":"HitTest","ts":103858820258,"dur":65,"x":3189,"y":75,"nodeName":"BODY id='pg-chrome_newtab' class='page-chrome_newtab body--home'","move":true},{"name":"UpdateLayerTree","dur":5,"ts":103858820448},{"name":"UpdateLayerTree","dur":6,"ts":103858836867},{"name":"HitTest","ts":103858836876,"dur":22,"x":2975,"y":75,"nodeName":"BODY id='pg-chrome_newtab' class='page-chrome_newtab body--home'","move":true},{"name":"UpdateLayerTree","dur":4,"ts":103858836987},{"name":"UpdateLayerTree","dur":6,"ts":103858853364},{"name":"HitTest","ts":103858853372,"dur":21,"x":2747,"y":75,"nodeName":"BODY id='pg-chrome_newtab' class='page-chrome_newtab body--home'","move":true},{"name":"UpdateLayerTree","dur":3,"ts":103858853445},{"name":"UpdateLayerTree","dur":6,"ts":103858870099},{"name":"HitTest","ts":103858870107,"dur":19,"x":2432,"y":136,"nodeName":"BODY id='pg-chrome_newtab' class='page-chrome_newtab body--home'","move":true},{"name":"UpdateLayerTree","dur":4,"ts":103858870179},{"name":"UpdateLayerTree","dur":6,"ts":103858886732},{"name":"HitTest","ts":103858886740,"dur":22,"x":2253,"y":189,"nodeName":"BODY id='pg-chrome_newtab' class='page-chrome_newtab body--home'","move":true},{"name":"UpdateLayerTree","dur":4,"ts":103858886874},{"name":"UpdateLayerTree","dur":7,"ts":103858903459},{"name":"HitTest","ts":103858903468,"dur":23,"x":2131,"y":224,"nodeName":"BODY id='pg-chrome_newtab' class='page-chrome_newtab body--home'","move":true},{"name":"UpdateLayerTree","dur":4,"ts":103858903612},{"name":"UpdateLayerTree","dur":40,"ts":103858920153},{"name":"HitTest","ts":103858920195,"dur":68,"x":1991,"y":276,"nodeName":"BODY id='pg-chrome_newtab' class='page-chrome_newtab body--home'","move":true},{"name":"UpdateLayerTree","dur":13,"ts":103858920344},{"name":"UpdateLayerTree","dur":7,"ts":103858936859},{"name":"HitTest","ts":103858936868,"dur":36,"x":1922,"y":308,"nodeName":"DIV class='logo-wrap--home'","move":true},{"name":"UpdateLayerTree","dur":4,"ts":103858937002},{"name":"UpdateLayerTree","dur":6,"ts":103858953336},{"name":"HitTest","ts":103858953344,"dur":22,"x":1873,"y":333,"nodeName":"A id='logo_homepage_link' class='logo_homepage'","move":true},{"name":"ScheduleStyleRecalculation","ts":103858953373},{"name":"UpdateLayerTree","dur":128,"ts":103858953803},{"name":"UpdateLayerTree","dur":10,"ts":103858970245},{"name":"HitTest","ts":103858970258,"dur":36,"x":1842,"y":347,"nodeName":"A id='logo_homepage_link' class='logo_homepage'","move":true},{"name":"UpdateLayerTree","dur":4,"ts":103858970400},{"name":"UpdateLayerTree","dur":6,"ts":103858986858},{"name":"HitTest","ts":103858986866,"dur":22,"x":1819,"y":355,"nodeName":"A id='logo_homepage_link' class='logo_homepage'","move":true},{"name":"UpdateLayerTree","dur":4,"ts":103858986973},{"name":"UpdateLayerTree","dur":6,"ts":103859003355},{"name":"HitTest","ts":103859003363,"dur":21,"x":1810,"y":358,"nodeName":"A id='logo_homepage_link' class='logo_homepage'","move":true},{"name":"UpdateLayerTree","dur":4,"ts":103859003468},{"name":"UpdateLayerTree","dur":18,"ts":103859020213},{"name":"HitTest","ts":103859020233,"dur":30,"x":1802,"y":360,"nodeName":"A id='logo_homepage_link' class='logo_homepage'","move":true},{"name":"UpdateLayerTree","dur":6,"ts":103859020407},{"name":"UpdateLayerTree","dur":13,"ts":103859036882},{"name":"HitTest","ts":103859036898,"dur":62,"x":1795,"y":363,"nodeName":"A id='logo_homepage_link' class='logo_homepage'","move":true},{"name":"UpdateLayerTree","dur":4,"ts":103859037122},{"name":"UpdateLayerTree","dur":6,"ts":103859053522},{"name":"HitTest","ts":103859053530,"dur":22,"x":1783,"y":368,"nodeName":"A id='logo_homepage_link' class='logo_homepage'","move":true},{"name":"UpdateLayerTree","dur":4,"ts":103859053640},{"name":"UpdateLayerTree","dur":6,"ts":103859070195},{"name":"HitTest","ts":103859070203,"dur":19,"x":1778,"y":371,"nodeName":"A id='logo_homepage_link' class='logo_homepage'","move":true},{"name":"UpdateLayerTree","dur":4,"ts":103859070304},{"name":"UpdateLayerTree","dur":9,"ts":103859086758},{"name":"HitTest","ts":103859086769,"dur":44,"x":1773,"y":374,"nodeName":"A id='logo_homepage_link' class='logo_homepage'","move":true},{"name":"UpdateLayerTree","dur":19,"ts":103859086982},{"name":"UpdateLayerTree","dur":6,"ts":103859103574},{"name":"HitTest","ts":103859103582,"dur":18,"x":1763,"y":384,"nodeName":"A id='logo_homepage_link' class='logo_homepage'","move":true},{"name":"UpdateLayerTree","dur":4,"ts":103859103690},{"name":"UpdateLayerTree","dur":6,"ts":103859120137},{"name":"HitTest","ts":103859120145,"dur":20,"x":1756,"y":400,"nodeName":"A id='logo_homepage_link' class='logo_homepage'","move":true},{"name":"UpdateLayerTree","dur":4,"ts":103859120247},{"name":"UpdateLayerTree","dur":6,"ts":103859136811},{"name":"HitTest","ts":103859136819,"dur":38,"x":1744,"y":425,"nodeName":"A id='logo_homepage_link' class='logo_homepage'","move":true},{"name":"UpdateLayerTree","dur":19,"ts":103859136949},{"name":"UpdateLayerTree","dur":5,"ts":103859153430},{"name":"HitTest","ts":103859153438,"dur":20,"x":1726,"y":478,"nodeName":"A id='logo_homepage_link' class='logo_homepage'","move":true},{"name":"UpdateLayerTree","dur":20,"ts":103859153580},{"name":"UpdateLayerTree","dur":6,"ts":103859170178},{"name":"HitTest","ts":103859170186,"dur":20,"x":1703,"y":544,"nodeName":"A id='logo_homepage_link' class='logo_homepage'","move":true},{"name":"UpdateLayerTree","dur":4,"ts":103859170296},{"name":"UpdateLayerTree","dur":7,"ts":103859186824},{"name":"HitTest","ts":103859186850,"dur":20,"x":1689,"y":589,"nodeName":"A id='logo_homepage_link' class='logo_homepage'","move":true},{"name":"UpdateLayerTree","dur":4,"ts":103859186954},{"name":"UpdateLayerTree","dur":9,"ts":103859203507},{"name":"HitTest","ts":103859203518,"dur":30,"x":1680,"y":622,"nodeName":"A id='logo_homepage_link' class='logo_homepage'","move":true},{"name":"UpdateLayerTree","dur":30,"ts":103859203662},{"name":"UpdateLayerTree","dur":6,"ts":103859220127},{"name":"HitTest","ts":103859220135,"dur":22,"x":1664,"y":688,"nodeName":"DIV class='search-wrap--home'","move":true},{"name":"ScheduleStyleRecalculation","ts":103859220163},{"name":"UpdateLayerTree","dur":116,"ts":103859220614},{"name":"UpdateLayerTree","dur":25,"ts":103859236800},{"name":"HitTest","ts":103859236827,"dur":25,"x":1656,"y":719,"nodeName":"DIV","move":true},{"name":"ScheduleStyleRecalculation","ts":103859236860},{"name":"InvalidateLayout","ts":103859308164},{"name":"Layout","ts":103859308203,"dirtyObjects":6,"dur":116,"hasStackTrace":true,"stackTrace":[{"functionName":"fix","scriptId":"7","url":"https://duckduckgo.com/lib/l113.js","lineNumber":26,"columnNumber":43301}]},{"name":"ScheduleStyleRecalculation","ts":103859308842},{"name":"UpdateLayerTree","dur":214,"ts":103859309162},{"name":"UpdateLayerTree","dur":22,"ts":103859320385},{"name":"HitTest","ts":103859320411,"dur":51,"x":1643,"y":794,"nodeName":"DIV","move":true},{"name":"UpdateLayerTree","dur":19,"ts":103859320642},{"name":"UpdateLayerTree","dur":13,"ts":103859336746},{"name":"HitTest","ts":103859336762,"dur":86,"x":1642,"y":797,"nodeName":"DIV","move":true},{"name":"UpdateLayerTree","dur":4,"ts":103859336958},{"name":"UpdateLayerTree","dur":10,"ts":103859353459},{"name":"HitTest","ts":103859353472,"dur":33,"x":1642,"y":799,"nodeName":"DIV","move":true},{"name":"UpdateLayerTree","dur":13,"ts":103859353580},{"name":"UpdateLayerTree","dur":13,"ts":103859369928},{"name":"HitTest","ts":103859369944,"dur":21,"x":1640,"y":799,"nodeName":"DIV","move":true},{"name":"UpdateLayerTree","dur":11,"ts":103859370053},{"name":"UpdateLayerTree","dur":7,"ts":103859386685},{"name":"HitTest","ts":103859386694,"dur":20,"x":1639,"y":799,"nodeName":"DIV","move":true},{"name":"UpdateLayerTree","dur":5,"ts":103859386859},{"name":"UpdateLayerTree","dur":6,"ts":103859413653},{"name":"UpdateLayerTree","dur":18,"ts":103859542419},{"name":"HitTest","ts":103859542439,"dur":35,"x":1639,"y":799,"nodeName":"DIV","move":false},{"name":"UpdateLayerTree","dur":14,"ts":103859542504},{"name":"HitTest","ts":103859542520,"dur":3,"x":1639,"y":799,"nodeName":"DIV","move":true},{"name":"UpdateLayerTree","dur":8,"ts":103859543156},{"name":"HitTest","ts":103859543166,"dur":6,"x":1639,"y":799,"nodeName":"DIV","move":true},{"name":"ScheduleStyleRecalculation","ts":103859543193},{"name":"ScheduleStyleRecalculation","ts":103859544038},{"name":"UpdateLayerTree","dur":56,"ts":103859544924},{"name":"UpdateLayerTree","dur":11,"ts":103859658677},{"name":"HitTest","ts":103859658690,"dur":30,"x":1639,"y":799,"nodeName":"DIV","move":false},{"name":"UpdateLayerTree","dur":9,"ts":103859660137},{"name":"UpdateLayerTree","dur":51,"ts":103860145419},{"name":"ScheduleStyleRecalculation","ts":103860193224},{"name":"ScheduleStyleRecalculation","ts":103860193502},{"name":"InvalidateLayout","ts":103860193528},{"name":"Layout","ts":103860193543,"dirtyObjects":3,"dur":104420,"hasStackTrace":false,"stackTrace":[]},{"name":"ScheduleStyleRecalculation","ts":103860298029},{"name":"InvalidateLayout","ts":103860298830},{"name":"Layout","ts":103860298857,"dirtyObjects":3,"dur":85,"hasStackTrace":false,"stackTrace":[]},{"name":"ScheduleStyleRecalculation","ts":103860298971},{"name":"ScheduleStyleRecalculation","ts":103860299572},{"name":"InvalidateLayout","ts":103860305640},{"name":"Layout","ts":103860305686,"dirtyObjects":9,"dur":327,"hasStackTrace":false,"stackTrace":[]},{"name":"UpdateLayerTree","dur":159,"ts":103860306112},{"name":"HitTest","ts":103860306275,"dur":27,"x":1639,"y":799,"nodeName":"DIV","move":true},{"name":"UpdateLayerTree","dur":7,"ts":103860306360},{"name":"UpdateLayerTree","dur":10,"ts":103860388419},{"name":"InvalidateLayout","ts":103860435475},{"name":"Layout","ts":103860435486,"dirtyObjects":3,"dur":130,"hasStackTrace":false,"stackTrace":[]},{"name":"ScheduleStyleRecalculation","ts":103860435648},{"name":"UpdateLayerTree","dur":76,"ts":103860436132},{"name":"HitTest","ts":103860436211,"dur":25,"x":1639,"y":799,"nodeName":"DIV","move":true},{"name":"UpdateLayerTree","dur":5,"ts":103860436274},{"name":"ScheduleStyleRecalculation","ts":103860459722},{"name":"ScheduleStyleRecalculation","ts":103860460246},{"name":"InvalidateLayout","ts":103860460444},{"name":"ScheduleStyleRecalculation","ts":103860460515},{"name":"InvalidateLayout","ts":103860464209},{"name":"ScheduleStyleRecalculation","ts":103860464447},{"name":"Layout","ts":103860475629,"dirtyObjects":94,"dur":30990,"hasStackTrace":false,"stackTrace":[]},{"name":"UpdateLayerTree","dur":414,"ts":103860506708},{"name":"HitTest","ts":103860507126,"dur":24,"x":1639,"y":799,"nodeName":"DIV","move":true},{"name":"UpdateLayerTree","dur":11,"ts":103860507193},{"name":"UpdateLayerTree","dur":14,"ts":103860541607},{"name":"ScheduleStyleRecalculation","ts":103860596585},{"name":"InvalidateLayout","ts":103860596936},{"name":"Layout","ts":103860597090,"dirtyObjects":6,"dur":102,"hasStackTrace":false,"stackTrace":[]},{"name":"UpdateLayerTree","dur":133,"ts":103860597292},{"name":"HitTest","ts":103860597429,"dur":25,"x":1639,"y":799,"nodeName":"DIV","move":true},{"name":"UpdateLayerTree","dur":5,"ts":103860597504},{"name":"ScheduleStyleRecalculation","ts":103860599454},{"name":"InvalidateLayout","ts":103860602495},{"name":"Layout","ts":103860609247,"dirtyObjects":90,"dur":878,"hasStackTrace":false,"stackTrace":[]},{"name":"UpdateLayerTree","dur":309,"ts":103860610242},{"name":"HitTest","ts":103860610556,"dur":28,"x":1639,"y":799,"nodeName":"DIV","move":true},{"name":"UpdateLayerTree","dur":6,"ts":103860610629},{"name":"InvalidateLayout","ts":103860614641},{"name":"Layout","ts":103860614671,"dirtyObjects":3,"dur":515,"hasStackTrace":false,"stackTrace":[]},{"name":"ScheduleStyleRecalculation","ts":103860615281},{"name":"UpdateLayerTree","dur":149,"ts":103860625545},{"name":"HitTest","ts":103860625700,"dur":63,"x":1639,"y":799,"nodeName":"DIV","move":true},{"name":"UpdateLayerTree","dur":7,"ts":103860625884},{"name":"UpdateLayerTree","dur":65,"ts":103860642277},{"name":"UpdateLayerTree","dur":26,"ts":103860708942},{"name":"ScheduleStyleRecalculation","ts":103860761246},{"name":"InvalidateLayout","ts":103860762398},{"name":"Layout","ts":103860762536,"dirtyObjects":6,"dur":96,"hasStackTrace":false,"stackTrace":[]},{"name":"UpdateLayerTree","dur":169,"ts":103860762740},{"name":"HitTest","ts":103860762912,"dur":23,"x":1639,"y":799,"nodeName":"DIV","move":true},{"name":"UpdateLayerTree","dur":5,"ts":103860762973},{"name":"ScheduleStyleRecalculation","ts":103860764072},{"name":"InvalidateLayout","ts":103860766927},{"name":"Layout","ts":103860776516,"dirtyObjects":92,"dur":1124,"hasStackTrace":false,"stackTrace":[]},{"name":"UpdateLayerTree","dur":452,"ts":103860777941},{"name":"HitTest","ts":103860778401,"dur":42,"x":1639,"y":799,"nodeName":"DIV","move":true},{"name":"UpdateLayerTree","dur":8,"ts":103860778511},{"name":"InvalidateLayout","ts":103860788674},{"name":"Layout","ts":103860788691,"dirtyObjects":3,"dur":214,"hasStackTrace":false,"stackTrace":[]},{"name":"ScheduleStyleRecalculation","ts":103860788948},{"name":"UpdateLayerTree","dur":87,"ts":103860792293},{"name":"HitTest","ts":103860792384,"dur":51,"x":1639,"y":799,"nodeName":"DIV","move":true},{"name":"UpdateLayerTree","dur":6,"ts":103860792506},{"name":"InvalidateLayout","ts":103860874915},{"name":"Layout","ts":103860874927,"dirtyObjects":3,"dur":129,"hasStackTrace":false,"stackTrace":[]},{"name":"ScheduleStyleRecalculation","ts":103860875089},{"name":"UpdateLayerTree","dur":75,"ts":103860875599},{"name":"HitTest","ts":103860875677,"dur":25,"x":1639,"y":799,"nodeName":"DIV","move":true},{"name":"UpdateLayerTree","dur":5,"ts":103860875737},{"name":"ScheduleStyleRecalculation","ts":103860954351},{"name":"InvalidateLayout","ts":103860954701},{"name":"Layout","ts":103860954904,"dirtyObjects":6,"dur":86,"hasStackTrace":false,"stackTrace":[]},{"name":"UpdateLayerTree","dur":106,"ts":103860955072},{"name":"HitTest","ts":103860955182,"dur":28,"x":1639,"y":799,"nodeName":"DIV","move":true},{"name":"UpdateLayerTree","dur":5,"ts":103860955247},{"name":"UpdateLayerTree","dur":39,"ts":103860966173},{"name":"ScheduleStyleRecalculation","ts":103860975618},{"name":"InvalidateLayout","ts":103860978671},{"name":"Layout","ts":103860981484,"dirtyObjects":92,"dur":717,"hasStackTrace":false,"stackTrace":[]},{"name":"UpdateLayerTree","dur":312,"ts":103860982292},{"name":"HitTest","ts":103860982608,"dur":31,"x":1639,"y":799,"nodeName":"DIV","move":true},{"name":"UpdateLayerTree","dur":5,"ts":103860982684},{"name":"UpdateLayerTree","dur":10,"ts":103861025554},{"name":"InvalidateLayout","ts":103861039554},{"name":"Layout","ts":103861039566,"dirtyObjects":3,"dur":87,"hasStackTrace":false,"stackTrace":[]},{"name":"ScheduleStyleRecalculation","ts":103861039686},{"name":"UpdateLayerTree","dur":92,"ts":103861042053},{"name":"HitTest","ts":103861042148,"dur":27,"x":1639,"y":799,"nodeName":"DIV","move":true},{"name":"UpdateLayerTree","dur":8,"ts":103861042216},{"name":"UpdateLayerTree","dur":71,"ts":103861058990},{"name":"UpdateLayerTree","dur":23,"ts":103861140384},{"name":"InvalidateLayout","ts":103861199938},{"name":"Layout","ts":103861199957,"dirtyObjects":3,"dur":144,"hasStackTrace":false,"stackTrace":[]},{"name":"ScheduleStyleRecalculation","ts":103861200149},{"name":"UpdateLayerTree","dur":69,"ts":103861200701},{"name":"HitTest","ts":103861200786,"dur":33,"x":1639,"y":799,"nodeName":"DIV","move":true},{"name":"UpdateLayerTree","dur":5,"ts":103861200863},{"name":"InvalidateLayout","ts":103861204033},{"name":"ScheduleStyleRecalculation","ts":103861204666},{"name":"Layout","ts":103861210994,"dirtyObjects":48,"dur":348,"hasStackTrace":false,"stackTrace":[]},{"name":"UpdateLayerTree","dur":200,"ts":103861211437},{"name":"HitTest","ts":103861211642,"dur":26,"x":1639,"y":799,"nodeName":"DIV","move":true},{"name":"UpdateLayerTree","dur":5,"ts":103861211718},{"name":"UpdateLayerTree","dur":15,"ts":103861300284},{"name":"InvalidateLayout","ts":103861407680},{"name":"ScheduleStyleRecalculation","ts":103861408122},{"name":"Layout","ts":103861411909,"dirtyObjects":47,"dur":307,"hasStackTrace":false,"stackTrace":[]},{"name":"UpdateLayerTree","dur":164,"ts":103861412295},{"name":"HitTest","ts":103861412463,"dur":25,"x":1639,"y":799,"nodeName":"DIV","move":true},{"name":"UpdateLayerTree","dur":8,"ts":103861412526},{"name":"UpdateLayerTree","dur":16,"ts":103861475469},{"name":"ScheduleStyleRecalculation","ts":103861548963},{"name":"InvalidateLayout","ts":103861554663},{"name":"Layout","ts":103861555763,"dirtyObjects":79,"dur":928,"hasStackTrace":false,"stackTrace":[]},{"name":"UpdateLayerTree","dur":313,"ts":103861556876},{"name":"HitTest","ts":103861557198,"dur":39,"x":1639,"y":799,"nodeName":"DIV","move":true},{"name":"UpdateLayerTree","dur":23,"ts":103861557323},{"name":"UpdateLayerTree","dur":9,"ts":103861557487},{"name":"ScheduleStyleRecalculation","ts":103861564248},{"name":"ScheduleStyleRecalculation","ts":103861565171},{"name":"ScheduleStyleRecalculation","ts":103861566551},{"name":"UpdateLayerTree","dur":16,"ts":103861567501}]}